pyp6xer_dev-1.15.0.dist-info/licenses/LICENSE
xerparser/__init__.py
xerparser/reader.py
xerparser/write.py
xerparser/dcma14/__init__.py
xerparser/dcma14/analysis.py
xerparser/model/__init__.py
xerparser/model/accounts.py
xerparser/model/activitiyresources.py
xerparser/model/activitycodes.py
xerparser/model/acttypes.py
xerparser/model/calendars.py
xerparser/model/currencies.py
xerparser/model/fintmpls.py
xerparser/model/nonworks.py
xerparser/model/obss.py
xerparser/model/pacttypes.py
xerparser/model/pcatvals.py
xerparser/model/predecessors.py
xerparser/model/projcats.py
xerparser/model/projects.py
xerparser/model/rcattypes.py
xerparser/model/rcatvals.py
xerparser/model/resources.py
xerparser/model/rolerates.py
xerparser/model/roles.py
xerparser/model/rsrccats.py
xerparser/model/rsrccurves.py
xerparser/model/rsrcrates.py
xerparser/model/schedoptions.py
xerparser/model/taskactvs.py
xerparser/model/taskprocs.py
xerparser/model/tasks.py
xerparser/model/udftypes.py
xerparser/model/udfvalues.py
xerparser/model/wbss.py
xerparser/model/classes/__init__.py
xerparser/model/classes/account.py
xerparser/model/classes/activitycode.py
xerparser/model/classes/acttype.py
xerparser/model/classes/calendar.py
xerparser/model/classes/calendar_data.py
xerparser/model/classes/currency.py
xerparser/model/classes/data.py
xerparser/model/classes/fintmpl.py
xerparser/model/classes/nonwork.py
xerparser/model/classes/obs.py
xerparser/model/classes/p6codes.py
xerparser/model/classes/pcattype.py
xerparser/model/classes/pcatval.py
xerparser/model/classes/projcat.py
xerparser/model/classes/project.py
xerparser/model/classes/rcattype.py
xerparser/model/classes/rcatval.py
xerparser/model/classes/role.py
xerparser/model/classes/rolerate.py
xerparser/model/classes/rsrc.py
xerparser/model/classes/rsrccurv.py
xerparser/model/classes/rsrcrate.py
xerparser/model/classes/rsrcrcat.py
xerparser/model/classes/schedoption.py
xerparser/model/classes/task.py
xerparser/model/classes/taskactv.py
xerparser/model/classes/taskpred.py
pyp6xer_dev-1.15.0.dist-info/METADATA
pyp6xer_dev-1.15.0.dist-info/WHEEL
pyp6xer_dev-1.15.0.dist-info/entry_points.txt
pyp6xer_dev-1.15.0.dist-info/top_level.txt
pyp6xer_dev-1.15.0.dist-info/RECORD
