Metadata-Version: 2.4
Name: PyP6Xer-dev
Version: 1.15.0
Summary: An actively maintained fork of PyP6Xer: A Python parser for Primavera XER files.
Author-email: Hassan <hassan.emam@hotmail.com>, Osama Ata <me@osamata.com>
License: GPL-3.0-or-later
Project-URL: Homepage, https://github.com/osama-ata/PyP6Xer-dev
Project-URL: Documentation, https://github.com/osama-ata/PyP6Xer-dev
Project-URL: Source, https://github.com/osama-ata/PyP6Xer-dev
Project-URL: Issues, https://github.com/osama-ata/PyP6Xer-dev/issues
Classifier: Programming Language :: Python :: 3
Classifier: Programming Language :: Python :: 3.8
Classifier: Programming Language :: Python :: 3.9
Classifier: Programming Language :: Python :: 3.10
Classifier: Programming Language :: Python :: 3.11
Classifier: Operating System :: OS Independent
Classifier: License :: OSI Approved :: GNU General Public License v3 or later (GPLv3+)
Classifier: Development Status :: 4 - Beta
Classifier: Intended Audience :: Developers
Classifier: Topic :: Software Development :: Libraries :: Python Modules
Requires-Python: >=3.8
License-File: LICENSE
Dynamic: license-file
